jobs/bigbang.py
jobs/create_requirements.py
jobs/enrich.py
jobs/megastar.py
jobs/megastorm.py
jobs/produce.py
jobs/rotate_pageviews/10to60/rotate_pg_page_10to60.py
jobs/rotate_pageviews/10to60/rotate_pg_section_10to60.py
jobs/rotate_pageviews/10to60/rotate_pg_website_10to60.py
jobs/rotate_pageviews/1to5/rotate_pg_page_1to5.py
jobs/rotate_pageviews/1to5/rotate_pg_section_1to5.py
jobs/rotate_pageviews/1to5/rotate_pg_website_1to5.py
jobs/rotate_pageviews/5to10/rotate_pg_page_5to10.py
jobs/rotate_pageviews/5to10/rotate_pg_section_5to10.py
jobs/rotate_pageviews/5to10/rotate_pg_website_5to10.py
jobs/rotate_pageviews/60to180/rotate_pg_page_60to180.py
jobs/rotate_pageviews/60to180/rotate_pg_section_60to180.py
jobs/rotate_pageviews/60to180/rotate_pg_website_60to180.py
jobs/rotate_unique_devices/10to60/rotate_ud_page_10to60.py
jobs/rotate_unique_devices/10to60/rotate_ud_section_10to60.py
jobs/rotate_unique_devices/10to60/rotate_ud_website_10to60.py
jobs/rotate_unique_devices/1to5/rotate_ud_page_1to5.py
jobs/rotate_unique_devices/1to5/rotate_ud_section_1to5.py
jobs/rotate_unique_devices/1to5/rotate_ud_website_1to5.py
jobs/rotate_unique_devices/5to10/rotate_ud_page_5to10.py
jobs/rotate_unique_devices/5to10/rotate_ud_section_5to10.py
jobs/rotate_unique_devices/5to10/rotate_ud_website_5to10.py
jobs/rotate_unique_devices/60to180/rotate_ud_page_60to180.py
jobs/rotate_unique_devices/60to180/rotate_ud_section_60to180.py
jobs/rotate_unique_devices/60to180/rotate_ud_website_60to180.py
jobs/sandbox/sandbox-player.py
jobs/sandbox/sandbox.py
jobs/sandbox/sandbox_page.py
jobs/sandbox/sandbox_section.py
jobs/sandbox/sandbox_website.py
jobs/sandbox/job_recovery/import_tracker_data.py
jobs/sandbox/job_recovery/streaming_job.py
rgtracker/__init__.py
rgtracker/common.py
rgtracker/device.py
rgtracker/page.py
rgtracker/pageviews.py
rgtracker/record.py
rgtracker/section.py
rgtracker/tracker.py
rgtracker/uniquedevices.py
rgtracker/website.py
rgtracker-0.0.1.1.226.dist-info/LICENSE
rgtracker-0.0.1.1.226.dist-info/METADATA
rgtracker-0.0.1.1.226.dist-info/WHEEL
rgtracker-0.0.1.1.226.dist-info/top_level.txt
rgtracker-0.0.1.1.226.dist-info/RECORD
